stylgebra/__init__.py
stylgebra/adapt.py
stylgebra/algebra.py
stylgebra/basic.py
stylgebra/elnt.py
stylgebra/excep.py
stylgebra/expressions.py
stylgebra/numerical.py
stylgebra/relations.py
stylgebra-0.1.0.dist-info/LICENSE
stylgebra-0.1.0.dist-info/METADATA
stylgebra-0.1.0.dist-info/NOTICE
stylgebra-0.1.0.dist-info/WHEEL
stylgebra-0.1.0.dist-info/top_level.txt
stylgebra-0.1.0.dist-info/RECORD
