Metadata-Version: 2.1
Name: stylgebra
Version: 0.1.0
Summary: Stylable algebraic expressions
Home-page: https://github.com/skieffer/stylgebra
License: Apache 2.0
Classifier: License :: OSI Approved :: Apache Software License
Classifier: Programming Language :: Python :: 3
License-File: LICENSE
License-File: NOTICE
Requires-Dist: sympy
Provides-Extra: dev
Requires-Dist: pytest ; extra == 'dev'
Requires-Dist: build ; extra == 'dev'
Requires-Dist: twine ; extra == 'dev'
Requires-Dist: invoke ; extra == 'dev'
